market_engine/Common.py
market_engine/ManifestParser.py
market_engine/__init__.py
market_engine/API/ManifestAPI.py
market_engine/API/MarketAPI.py
market_engine/API/RelicsRunAPI.py
market_engine/API/__init__.py
market_engine/Models/MarketDatabase.py
market_engine/Models/MarketItem.py
market_engine/Models/MarketUser.py
market_engine/Models/__init__.py
market_engine-0.1.72.dist-info/METADATA
market_engine-0.1.72.dist-info/WHEEL
market_engine-0.1.72.dist-info/top_level.txt
market_engine-0.1.72.dist-info/RECORD
