Metadata-Version: 2.4
Name: market-engine
Version: 0.1.72
Summary: Engine for easily getting the orders, statistics, and other stats from warframe.market.
Author: Jacob McBride
Author-email: jake55111@gmail.com
Requires-Dist: aiohttp==3.10.11
Requires-Dist: aiolimiter~=1.1.0
Requires-Dist: redis~=5.0.3
Requires-Dist: requests==2.32.4
Requires-Dist: beautifulsoup4~=4.12.2
Requires-Dist: PyMySQL~=1.1.0
Requires-Dist: fuzzywuzzy~=0.18.0
Requires-Dist: pytz~=2023.3
Requires-Dist: python-Levenshtein~=0.25.0
Requires-Dist: beautifulsoup4~=4.12.2
Requires-Dist: Markdown~=3.4.3
Requires-Dist: cryptography==44.0.1
Requires-Dist: tenacity~=8.2.2
Requires-Dist: pymysql-pool~=0.4.6
Dynamic: author
Dynamic: author-email
Dynamic: requires-dist
Dynamic: summary
